windmill_api/__init__.py
windmill_api/api/__init__.py
windmill_api/api/app/__init__.py
windmill_api/api/app/create_app.py
windmill_api/api/app/delete_app.py
windmill_api/api/app/execute_component.py
windmill_api/api/app/exists_app.py
windmill_api/api/app/get_app_by_path.py
windmill_api/api/app/get_app_by_path_with_draft.py
windmill_api/api/app/get_app_by_version.py
windmill_api/api/app/get_app_history_by_path.py
windmill_api/api/app/get_hub_app_by_id.py
windmill_api/api/app/get_public_app_by_secret.py
windmill_api/api/app/get_public_resource.py
windmill_api/api/app/get_public_secret_of_app.py
windmill_api/api/app/list_apps.py
windmill_api/api/app/list_hub_apps.py
windmill_api/api/app/list_search_app.py
windmill_api/api/app/update_app.py
windmill_api/api/app/update_app_history.py
windmill_api/api/audit/__init__.py
windmill_api/api/audit/get_audit_log.py
windmill_api/api/audit/list_audit_logs.py
windmill_api/api/capture/__init__.py
windmill_api/api/capture/create_capture.py
windmill_api/api/capture/get_capture.py
windmill_api/api/capture/update_capture.py
windmill_api/api/config/__init__.py
windmill_api/api/config/delete_config.py
windmill_api/api/config/get_config.py
windmill_api/api/config/list_worker_groups.py
windmill_api/api/config/update_config.py
windmill_api/api/draft/__init__.py
windmill_api/api/draft/create_draft.py
windmill_api/api/draft/delete_draft.py
windmill_api/api/favorite/__init__.py
windmill_api/api/favorite/star.py
windmill_api/api/favorite/unstar.py
windmill_api/api/flow/__init__.py
windmill_api/api/flow/archive_flow_by_path.py
windmill_api/api/flow/create_flow.py
windmill_api/api/flow/delete_flow_by_path.py
windmill_api/api/flow/exists_flow_by_path.py
windmill_api/api/flow/get_flow_by_path.py
windmill_api/api/flow/get_flow_by_path_with_draft.py
windmill_api/api/flow/get_flow_input_history_by_path.py
windmill_api/api/flow/get_hub_flow_by_id.py
windmill_api/api/flow/list_flow_paths.py
windmill_api/api/flow/list_flows.py
windmill_api-1.233.0.dist-info/LICENSE
windmill_api-1.233.0.dist-info/METADATA
windmill_api-1.233.0.dist-info/WHEEL
windmill_api-1.233.0.dist-info/RECORD
