Metadata-Version: 2.1
Name: windmill-api
Version: 1.233.0
Summary: A client library for accessing Windmill API
License: Apache-2.0
Author: Ruben Fiszel
Author-email: ruben@windmill.dev
Requires-Python: >=3.8,<4.0
Classifier: License :: OSI Approved :: Apache Software License
Classifier: Programming Language :: Python :: 3
Classifier: Programming Language :: Python :: 3.8
Classifier: Programming Language :: Python :: 3.9
Classifier: Programming Language :: Python :: 3.10
Classifier: Programming Language :: Python :: 3.11
Requires-Dist: attrs (>=21.3.0)
Requires-Dist: httpx (>=0.20.0,<0.25.0)
Requires-Dist: python-dateutil (>=2.8.0,<3.0.0)
